MANIFEST.in
README
setup.py
GoogleAppEnginePipeline.egg-info/PKG-INFO
GoogleAppEnginePipeline.egg-info/SOURCES.txt
GoogleAppEnginePipeline.egg-info/dependency_links.txt
GoogleAppEnginePipeline.egg-info/requires.txt
GoogleAppEnginePipeline.egg-info/top_level.txt
GoogleAppEnginePipeline.egg-info/zip-safe
pipeline/__init__.py
pipeline/common.py
pipeline/handlers.py
pipeline/models.py
pipeline/pipeline.py
pipeline/status_ui.py
pipeline/util.py
pipeline/simplejson/__init__.py
pipeline/simplejson/decoder.py
pipeline/simplejson/encoder.py
pipeline/simplejson/ordered_dict.py
pipeline/simplejson/scanner.py
pipeline/simplejson/tool.py
pipeline/ui/common.css
pipeline/ui/common.js
pipeline/ui/jquery-1.4.2.min.js
pipeline/ui/jquery.ba-hashchange.min.js
pipeline/ui/jquery.cookie.js
pipeline/ui/jquery.json.min.js
pipeline/ui/jquery.timeago.js
pipeline/ui/jquery.treeview.css
pipeline/ui/jquery.treeview.min.js
pipeline/ui/root_list.css
pipeline/ui/root_list.html
pipeline/ui/root_list.js
pipeline/ui/status.css
pipeline/ui/status.html
pipeline/ui/status.js
pipeline/ui/images/treeview-black-line.gif
pipeline/ui/images/treeview-black.gif
pipeline/ui/images/treeview-default-line.gif
pipeline/ui/images/treeview-default.gif